AUTHORS.rst
CONTRIBUTING.rst
HISTORY.rst
LICENSE
MANIFEST.in
README.rst
requirements_dev.txt
requirements_prod.txt
setup.cfg
setup.py
cnt.sam.egg-info/PKG-INFO
cnt.sam.egg-info/SOURCES.txt
cnt.sam.egg-info/dependency_links.txt
cnt.sam.egg-info/not-zip-safe
cnt.sam.egg-info/requires.txt
cnt.sam.egg-info/top_level.txt
cnt/sam/__init__.py
cnt/sam/cnt_sam.py
cnt/sam/cpp11/main.cc
cnt/sam/cpp11/sam.cc
cnt/sam/cpp11/sam.h
docs/Makefile
docs/authors.rst
docs/conf.py
docs/contributing.rst
docs/history.rst
docs/index.rst
docs/installation.rst
docs/make.bat
docs/readme.rst
docs/usage.rst
tests/test_cnt_sam.py
tests/test_cpp11_sam_impl.py