Metadata-Version: 1.1
Name: cnt.sam
Version: 0.1.2
Summary: None
Home-page: https://github.com/cnt-dev/cnt.sam
Author: Hunt Zhan
Author-email: huntzhan.dev@gmail.com
License: MIT license
Keywords: cnt.sam
Platform: UNKNOWN
Classifier: Development Status :: 2 - Pre-Alpha
Classifier: Intended Audience :: Developers
Classifier: License :: OSI Approved :: MIT License
Classifier: Natural Language :: English
Classifier: Programming Language :: Python :: 3
Classifier: Programming Language :: Python :: 3.6
Classifier: Programming Language :: Python :: 3.7
